recache/__init__.py
recache-1.0.0.dist-info/LICENSE
recache-1.0.0.dist-info/METADATA
recache-1.0.0.dist-info/WHEEL
recache-1.0.0.dist-info/top_level.txt
recache-1.0.0.dist-info/RECORD
