Metadata-Version: 2.1
Name: recache
Version: 1.0.0
Summary: Cache functions to speed up recursion
Home-page: https://github.com/donno2048/recache
Author: Elisha Hollander
License: MIT
Platform: UNKNOWN
Classifier: Programming Language :: Python :: 3
